Workbook

Sheet Summary
B2: Alaska Air Group (ALK) — Q2 2026 Guidance vs. Actual
B3: Variance analysis of management guidance (Apr 20, 2026) against reported Q2 2026 results (Jul 21, 2026). Adjusted (non-GAAP) basis.
B4: Prepared by: Brett Tierce | October 16, 2026
B6: Headline metric | C6: Guidance | D6: Actual | E6: Variance | F6: F / U
B7: Capacity (ASMs) y/y | C7: =Inputs!$C$10 -> 0.01 | D7: =IFERROR(Inputs!$C$24/Inputs!$C$5-1,0) -> 0.010308421 | E7: =D7-C7 -> 0.00030842132
B8: Unit revenue (RASM) y/y | C8: =Inputs!$C$11 -> 0.09 | D8: =IFERROR(Inputs!$C$25/Inputs!$C$6-1,0) -> 0.086419753 | E8: =D8-C8 -> -0.0035802469 | F8: =IF(ROUND(E8,6)=0,"-",IF(E8*1>0,"F","U")) -> U
B9: Unit cost (CASMex) y/y | C9: =Inputs!$C$14 -> 0.078 | D9: =IFERROR(Inputs!$C$26/Inputs!$C$7-1,0) -> 0.065420561 | E9: =D9-C9 -> -0.012579439 | F9: =IF(ROUND(E9,6)=0,"-",IF(E9*-1>0,"F","U")) -> F
B10: Economic fuel cost per gallon | C10: =Inputs!$C$15 -> 4.5 | D10: =Inputs!$C$27 -> 4.43 | E10: =D10-C10 -> -0.07 | F10: =IF(ROUND(E10,6)=0,"-",IF(E10*-1>0,"F","U")) -> F
B11: Adjusted pretax income ($mm, model) | C11: =Variance!C19 -> -185.13292 | D11: =Variance!D19 -> -175.7708 | E11: =D11-C11 -> 9.3621151 | F11: =IF(ROUND(E11,6)=0,"-",IF(E11*1>0,"F","U")) -> F
B12: Adjusted EPS (guided vs. reported) | C12: =Inputs!$C$18 -> -1 | D12: =Inputs!$C$34 -> -0.92 | E12: =D12-C12 -> 0.08 | F12: =IF(ROUND(E12,6)=0,"-",IF(E12*1>0,"F","U")) -> F
B13: y/y actuals computed vs. Q2 2025 baseline on Inputs tab; percentage variances shown in points.
B15: Key takeaways
B16: 1. EPS guidance beat from taxes, not operations | C16: Adjusted EPS of -$0.92 beat the model budget (-$1.10). About $0.15 of the $0.18 improvement came from a 42% tax rate on the pretax loss vs. 32% planned. Pretax income was only $9M better than plan. That makes the beat low quality and not repeatable: the tax effect reverses once Alaska returns to profitability.
B17: 2. Strong increase in unit revenues despite missed midpoint | C17: Unit revenues grew 8.6%, slightly unfavorable to 9% midpoint, but fits "high single digits" expectation. With capacity growth up only 1%, unit revenue growth came from pricing and mix: premium revenue rose 15% and cargo revenue 21%. Expect low double digit growth for Q3.
B18: 3. Strong cost control offset by incentive pay & softer unit revenue | C18: Strong cost management brought non-fuel operating costs in $32M (1.1%) under forecast. Fuel cost came in $30M (2.2%) under forecast. If cost management continues Q3 CASMex assumptions may be conservative. Savings on cost were offset by higher performance-based pay ($35M), higher interest expense from new financing ($5M), and unit revenues slightly below forecast.
B37: Color legend
B38: Blue text | C38: Input cell - Hard-Coded
B39: Black text | C39: Formula
B40: Green text | C40: Cross Sheet Reference
B42: Sources
B43: Alaska Air Group, Form 8-K Ex. 99.1, Q1 2026 earnings release (Apr 20, 2026)
B44: Alaska Air Group, Form 8-K Ex. 99.1, Q2 2026 earnings release (Jul 21, 2026)

Sheet Inputs
A1: Inputs
A3: Line item | B3: Unit | C3: Value | D3: Source & Notes
A4: A. Prior-year baseline — Q2 2025 actual
A5: ASMs (capacity) | B5: mm | C5: 24058 | D5: EX 99.1 7/21/2026 Earnings Release; Operating Statistics
A6: RASM (unit revenue) | B6: ¢ | C6: 15.39 | D6: EX 99.1 7/21/2026 Earnings Release; Operating Statistics
A7: CASMex (non-fuel unit cost) | B7: ¢ | C7: 10.7 | D7: EX 99.1 7/21/2026 Earnings Release; Operating Statistics
A9: B. Budget — Q2 2026 forecast
A10: Capacity (ASMs) growth y/y | B10: % | C10: 0.01 | D10: EX 99.1 4/20/2026 Earnings Release; Second Quarter Forecast Information
A11: RASM growth y/y (midpoint) | B11: % | C11: 0.09 | D11: EX 99.1 4/20/2026 Earnings Release; Second Quarter Forecast Information Midpoint from 8-10%
A12: Q1 2026 CASMex growth y/y (base for guidance) | B12: % | C12: 0.063 | D12: EX 99.1 4/20/2026 Earnings Release; Operating Statistics
A13: Guided CASMex increment vs. Q1 | B13: pts | C13: 0.015 | D13: EX 99.1 4/20/2026 Earnings Release; Second Quarter Forecast Information
A14: Implied CASMex growth y/y | B14: % | C14: =$C$12+$C$13 -> 0.078
A15: Economic fuel cost per gallon | B15: $/gal | C15: 4.5 | D15: EX 99.1 4/20/2026 Earnings Release; Second Quarter Forecast Information
A16: Fuel gallons consumed | B16: mm | C16: 297 | D16: EX 99.1 4/20/2026 Earnings Release; Second Quarter Forecast Information
A17: Tax rate | B17: % | C17: 0.32 | D17: EX 99.1 4/20/2026 Earnings Release; Second Quarter Forecast Information
A18: Guided adjusted EPS | B18: $/sh | C18: -1 | D18: EX 99.1 4/20/2026 Earnings Release; Second Quarter forecast Information
A19: Freighter costs + performance-based pay (assumption) | B19: $mm | C19: 81 | D19: EX 99.1 4/20/2026 Earnings Release; CASMex Reconciliation Assumes Q1 Run-Rate
A20: Non-operating expense, net, excl. FX (assumption) | B20: $mm | C20: 41 | D20: EX 99.1 4/20/2026 Earnings Release, Condensed Consolidated Statement of Operations Assumes Q1 Run-Rate
A21: Diluted shares (assumption) | B21: mm | C21: 114.294 | D21: EX 99.1 4/20/2026 Earnings Release; Condensed Consolidated Statement of Operations Assumes Q1 Run-Rate
A23: C. Actual — Q2 2026 results (Q2 2026 release, Jul 21, 2026)
A24: ASMs (capacity) | B24: mm | C24: 24306 | D24: EX 99.1 7/21/2026 Earnings Release; Operating Statistics
A25: RASM (unit revenue) | B25: ¢ | C25: 16.72 | D25: EX 99.1 7/21/2026 Earnings Release; Operating Statistics
A26: CASMex (non-fuel unit cost) | B26: ¢ | C26: 11.4 | D26: EX 99.1 7/21/2026 Earnings Release; Operating Statistics
A27: Economic fuel cost per gallon | B27: $/gal | C27: 4.43 | D27: EX 99.1 7/21/2026 Earnings Release; Operating Statistics
A28: Fuel gallons consumed | B28: mm | C28: 295 | D28: EX 99.1 7/21/2026 Earnings Release; Operating Statistics
A29: Freighter costs + performance-based pay | B29: $mm | C29: 116 | D29: EX 99.1 7/21/2026 Earnings Release; CASMex Reconciliation
A30: Non-operating expense, net, excl. FX | B30: $mm | C30: 46 | D30: EX 99.1 7/21/2026 Earnings Release; Condensed Consolidated Statement of Operations
A31: Adjusted tax rate (adj. tax ÷ adj. pretax) | B31: % | C31: 0.42045 | D31: EX 99.1 7/21/2026 Earnings Release; GAAP-to-non-GAAP Reconciliation
A32: Diluted shares | B32: mm | C32: 111.127 | D32: EX 99.1 7/21/2026 Earnings Release; Condensed Consolidated Statement of Operations
A33: Reported adjusted pretax income (check) | B33: $mm | C33: -176 | D33: EX 99.1 7/21/2026 Earnings Release; GAAP-to-non-GAAP Reconciliation
A34: Reported adjusted EPS (check) | B34: $/sh | C34: -0.92 | D34: EX 99.1 7/21/2026 Earnings Release; GAAP-to-non-GAAP Reconciliation
A35: Reported total operating revenue (check) | B35: $mm | C35: 4065 | D35: EX 99.1 7/21/2026 Earnings Release; Condensed Consolidated Statement of Operations

Sheet Variance
A1: Budget (Guidance) vs. Actual — Q2 2026
A2: F = favorable, U = unfavorable
A4: Line item | B4: Unit | C4: Budget | D4: Actual | E4: Variance | F4: Var % | G4: F / U | H4: Commentary (driver explanation) | I4: Sign
A5: Operating drivers
A6: ASMs (capacity) | B6: mm | C6: =Inputs!$C$5*(1+Inputs!$C$10) -> 24298.58 | D6: =Inputs!$C$24 -> 24306 | E6: =D6-C6 -> 7.42 | F6: =IFERROR(E6/ABS(C6),"") -> 0.00030536764 | G6: =IF(I6=0,"",IF(ROUND(E6,6)=0,"-",IF(E6*I6>0,"F","U"))) | H6: Capacity grew ~1%, on budget, with no meaningful impact on earnings | I6: 0
A7: RASM | B7: ¢ | C7: =Inputs!$C$6*(1+Inputs!$C$11) -> 16.7751 | D7: =Inputs!$C$25 -> 16.72 | E7: =D7-C7 -> -0.0551 | F7: =IFERROR(E7/ABS(C7),"") -> -0.0032846302 | G7: =IF(I7=0,"",IF(ROUND(E7,6)=0,"-",IF(E7*I7>0,"F","U"))) -> U | H7: Unit revenues grew 8.6%, slightly unfavorable to 9% midpoint, but fits "high single digits" expectation. | I7: 1
A8: CASMex | B8: ¢ | C8: =Inputs!$C$7*(1+Inputs!$C$14) -> 11.5346 | D8: =Inputs!$C$26 -> 11.4 | E8: =D8-C8 -> -0.1346 | F8: =IFERROR(E8/ABS(C8),"") -> -0.011669239 | G8: =IF(I8=0,"",IF(ROUND(E8,6)=0,"-",IF(E8*I8>0,"F","U"))) -> F | H8: CASMex grew 6.5% vs 7.8% forecasted growth. Strong cost management minimized increases due to transitory factors | I8: -1
A9: Fuel cost per gallon | B9: $/gal | C9: =Inputs!$C$15 -> 4.5 | D9: =Inputs!$C$27 -> 4.43 | E9: =D9-C9 -> -0.07 | F9: =IFERROR(E9/ABS(C9),"") -> -0.015555556 | G9: =IF(I9=0,"",IF(ROUND(E9,6)=0,"-",IF(E9*I9>0,"F","U"))) -> F | H9: Fuel cost rose 85% adding $600M in cost; an expected significant increase, but 1.6% lower than forecast | I9: -1
A10: Fuel gallons | B10: mm | C10: =Inputs!$C$16 -> 297 | D10: =Inputs!$C$28 -> 295 | E10: =D10-C10 -> -2 | F10: =IFERROR(E10/ABS(C10),"") -> -0.0067340067 | G10: =IF(I10=0,"",IF(ROUND(E10,6)=0,"-",IF(E10*I10>0,"F","U"))) -> F | H10: Fuel consumption below budget by 2M gallons; on target for current capacity plan | I10: -1
A12: Adjusted P&L ($mm)
A13: Total operating revenue | B13: $mm | C13: =C6*C7/100 -> 4076.1111 | D13: =D6*D7/100 -> 4063.9632 | E13: =D13-C13 -> -12.147894 | F13: =IFERROR(E13/ABS(C13),"") -> -0.0029802656 | G13: =IF(I13=0,"",IF(ROUND(E13,6)=0,"-",IF(E13*I13>0,"F","U"))) -> U | H13: Operating revenue grew ~10%, $12M below forecast because of a slight RASM shortfall | I13: 1
A14: Non-fuel operating costs (CASMex basis) | B14: $mm | C14: =C6*C8/100 -> 2802.744 | D14: =D6*D8/100 -> 2770.884 | E14: =D14-C14 -> -31.860009 | F14: =IFERROR(E14/ABS(C14),"") -> -0.011367434 | G14: =IF(I14=0,"",IF(ROUND(E14,6)=0,"-",IF(E14*I14>0,"F","U"))) -> F | H14: Non-fuel costs were $32M under forecast because of strong cost management | I14: -1
A15: Aircraft fuel | B15: $mm | C15: =C10*C9 -> 1336.5 | D15: =D10*D9 -> 1306.85 | E15: =D15-C15 -> -29.65 | F15: =IFERROR(E15/ABS(C15),"") -> -0.022184811 | G15: =IF(I15=0,"",IF(ROUND(E15,6)=0,"-",IF(E15*I15>0,"F","U"))) -> F | H15: Fuel costs were $30M under forecast due to lower fuel cost and consumption | I15: -1
A16: Freighter costs + performance-based pay | B16: $mm | C16: =Inputs!$C$19 -> 81 | D16: =Inputs!$C$29 -> 116 | E16: =D16-C16 -> 35 | F16: =IFERROR(E16/ABS(C16),"") -> 0.43209877 | G16: =IF(I16=0,"",IF(ROUND(E16,6)=0,"-",IF(E16*I16>0,"F","U"))) -> U | H16: $35M above forecasted costs; entirely tied to performance-based pay, likely due to strong operational performance | I16: -1
A17: Adjusted operating income | B17: $mm | C17: =C13-C14-C15-C16 -> -144.13292 | D17: =D13-D14-D15-D16 -> -129.7708 | E17: =D17-C17 -> 14.362115 | F17: =IFERROR(E17/ABS(C17),"") -> 0.099644936 | G17: =IF(I17=0,"",IF(ROUND(E17,6)=0,"-",IF(E17*I17>0,"F","U"))) -> F | H17: Operating income 10% above forecast; cost management and lower fuel price more than offset unit revenue shortfall | I17: 1
A18: Non-operating expense, net | B18: $mm | C18: =Inputs!$C$20 -> 41 | D18: =Inputs!$C$30 -> 46 | E18: =D18-C18 -> 5 | F18: =IFERROR(E18/ABS(C18),"") -> 0.12195122 | G18: =IF(I18=0,"",IF(ROUND(E18,6)=0,"-",IF(E18*I18>0,"F","U"))) -> U | H18: Non-operating expenses $5M above budget due to higher interest expense on $1B of new financing in Q2 | I18: -1
A19: Adjusted pretax income | B19: $mm | C19: =C17-C18 -> -185.13292 | D19: =D17-D18 -> -175.7708 | E19: =D19-C19 -> 9.3621151 | F19: =IFERROR(E19/ABS(C19),"") -> 0.050569695 | G19: =IF(I19=0,"",IF(ROUND(E19,6)=0,"-",IF(E19*I19>0,"F","U"))) -> F | H19: Pretax income 5.1% above budget; tied to cost management but partly offset by an increase in performance-based pay | I19: 1
A20: Tax rate | B20: % | C20: =Inputs!$C$17 -> 0.32 | D20: =Inputs!$C$31 -> 0.42045 | E20: =D20-C20 -> 0.10045 | G20: =IF(I20=0,"",IF(ROUND(E20,6)=0,"-",IF(E20*I20>0,"F","U"))) | H20: Tax rate 42% vs 32% budget; higher rate raises tax benefit on pretax loss | I20: 0
A21: Income tax expense / (benefit) | B21: $mm | C21: =C19*C20 -> -59.242533 | D21: =D19*D20 -> -73.902833 | E21: =D21-C21 -> -14.6603 | F21: =IFERROR(E21/ABS(C21),"") -> -0.24746241 | G21: =IF(I21=0,"",IF(ROUND(E21,6)=0,"-",IF(E21*I21>0,"F","U"))) | H21: $15M higher benefit than plan due to higher rate on pretax loss | I21: 0
A22: Adjusted net income | B22: $mm | C22: =C19-C21 -> -125.89038 | D22: =D19-D21 -> -101.86797 | E22: =D22-C22 -> 24.022415 | F22: =IFERROR(E22/ABS(C22),"") -> 0.1908201 | G22: =IF(I22=0,"",IF(ROUND(E22,6)=0,"-",IF(E22*I22>0,"F","U"))) -> F | H22: Adjusted net income 19.1% higher than forecast due to tax benefit | I22: 1
A23: Diluted shares | B23: mm | C23: =Inputs!$C$21 -> 114.294 | D23: =Inputs!$C$32 -> 111.127 | E23: =D23-C23 -> -3.167 | F23: =IFERROR(E23/ABS(C23),"") -> -0.027709241 | G23: =IF(I23=0,"",IF(ROUND(E23,6)=0,"-",IF(E23*I23>0,"F","U"))) | H23: A decrease in diluted shares by 3.2M due to Q1 share repurchases | I23: 0
A24: Adjusted EPS (model) | B24: $/sh | C24: =IFERROR(C22/C23,0) -> -1.101461 | D24: =IFERROR(D22/D23,0) -> -0.91668062 | E24: =D24-C24 -> 0.18478037 | F24: =IFERROR(E24/ABS(C24),"") -> 0.16775934 | G24: =IF(I24=0,"",IF(ROUND(E24,6)=0,"-",IF(E24*I24>0,"F","U"))) -> F | H24: $0.18 favorable vs. model budget ($0.08 vs. -$1.00 guide): +$0.15 tax, +$0.06 operations, -$0.03 share count | I24: 1
A26: Check | B26: Unit | C26: Reported | D26: Model | E26: Difference
A27: Budget EPS: guided vs. model-implied | B27: $/sh | C27: =Inputs!$C$18 -> -1 | D27: =C24 -> -1.101461 | E27: =C27-D27 -> 0.10146099
A28: Actual EPS: reported vs. model | B28: $/sh | C28: =Inputs!$C$34 -> -0.92 | D28: =D24 -> -0.91668062 | E28: =C28-D28 -> -0.0033193811
A29: Actual pretax: reported vs. model | B29: $mm | C29: =Inputs!$C$33 -> -176 | D29: =D19 -> -175.7708 | E29: =C29-D29 -> -0.2292
A30: Actual revenue: reported vs. model | B30: $mm | C30: =Inputs!$C$35 -> 4065 | D30: =D13 -> 4063.9632 | E30: =C30-D30 -> 1.0368
A32: Gap = unguided assumptions (PBP, non-op, shares)

Sheet Bridge
A1: Guidance-to-Actual Bridge — Q2 2026
A2: Volume effects at budget rates; rate effects at actual volumes. Positive = helped earnings vs. guidance.
A4: Driver | B4: Pretax impact ($mm) | C4: EPS impact ($/sh) | D4: % of EPS var. | E4: Commentary | F4: Chart label
A5: Budget (guidance-based model) | B5: =Variance!$C$19 -> -185.13292 | C5: =Variance!$C$24 -> -1.101461
A6: Capacity — revenue volume | B6: =(Variance!$D$6-Variance!$C$6)*Variance!$C$7/100 -> 1.2447124 | C6: =IFERROR(B6*(1-Variance!$C$20)/Variance!$C$23,0) -> 0.007405502 | D6: =IFERROR(C6/(C$16-C$5),"") -> 0.04007732 | E6: Capacity plan < 5% of EPS variance; on budget with no forecast change needed | F6: Capacity (Rev)
A7: Unit revenue (RASM) — rate | B7: =(Variance!$D$7-Variance!$C$7)*Variance!$D$6/100 -> -13.392606 | C7: =IFERROR(B7*(1-Variance!$C$20)/Variance!$C$23,0) -> -0.079680229 | D7: =IFERROR(C7/(C$16-C$5),"") -> -0.43121587 | E7: Second largest unfavorable driver, partly due to Hawaii storms. Low double digit growth expected for Q3; for forecast use a more conservative midpoint | F7: RASM
A8: Capacity — non-fuel cost volume | B8: =-(Variance!$D$6-Variance!$C$6)*Variance!$C$8/100 -> -0.85586732 | C8: =IFERROR(B8*(1-Variance!$C$20)/Variance!$C$23,0) -> -0.0050920414 | D8: =IFERROR(C8/(C$16-C$5),"") -> -0.027557264 | E8: Capacity plan < 5% of EPS variance; on budget with no forecast change needed | F8: Capacity (Cost)
A9: Unit cost (CASMex) — rate | B9: =-(Variance!$D$8-Variance!$C$8)*Variance!$D$6/100 -> 32.715876 | C9: =IFERROR(B9*(1-Variance!$C$20)/Variance!$C$23,0) -> 0.19464535 | D9: =IFERROR(C9/(C$16-C$5),"") -> 1.0533876 | E9: Strongest favorable driver from cost management; if cost management continues Q3 CASMex assumptions may be conservative | F9: CASMex
A10: Fuel price | B10: =-(Variance!$D$9-Variance!$C$9)*Variance!$D$10 -> 20.65 | C10: =IFERROR(B10*(1-Variance!$C$20)/Variance!$C$23,0) -> 0.12285859 | D10: =IFERROR(C10/(C$16-C$5),"") -> 0.66488985 | E10: External favorable factor; fuel remains volatile and should be stress-tested in Q3 | F10: Fuel Price
A11: Fuel consumption | B11: =-(Variance!$D$10-Variance!$C$10)*Variance!$C$9 -> 9 | C11: =IFERROR(B11*(1-Variance!$C$20)/Variance!$C$23,0) -> 0.053546118 | D11: =IFERROR(C11/(C$16-C$5),"") -> 0.2897825 | E11: Small factor partly controllable with the modernization of aircraft fleet; expect continued moderate benefit | F11: Fuel Volume
A12: Freighter costs + performance-based pay | B12: =-(Variance!$D$16-Variance!$C$16) -> -35 | C12: =IFERROR(B12*(1-Variance!$C$20)/Variance!$C$23,0) -> -0.2082349 | D12: =IFERROR(C12/(C$16-C$5),"") -> -1.126932 | E12: Largest unfavorable factor offsetting CASMex performance. Entirely tied to a large swing in performance-based pay from a light Q1. | F12: Freighter/PBP
A13: Non-operating expense | B13: =-(Variance!$D$18-Variance!$C$18) -> -5 | C13: =IFERROR(B13*(1-Variance!$C$20)/Variance!$C$23,0) -> -0.029747843 | D13: =IFERROR(C13/(C$16-C$5),"") -> -0.16099028 | E13: Higher interest expense from $1B in new financing that will continue into Q3 and later | F13: Non-Op
A14: Tax rate | C14: =IFERROR(Variance!$D$19*(Variance!$C$20-Variance!$D$20)/Variance!$C$23,0) -> 0.15448035 | D14: =IFERROR(C14/(C$16-C$5),"") -> 0.83602142 | E14: Majority reason for EPS movement; non-operational factor & non-repeatable. A higher rate is a benefit in a loss quarter but a negative when profitable
A15: Share count | C15: =IFERROR(Variance!$D$19*(1-Variance!$D$20)*(1/Variance!$D$23-1/Variance!$C$23),0) -> -0.025400524 | D15: =IFERROR(C15/(C$16-C$5),"") -> -0.13746333 | E15: Small expected factor from Q1 buybacks; work announced repurchases into budget's share assumption
A16: Actual (model) | B16: =SUM(B5:B15) -> -175.7708 | C16: =SUM(C5:C15) -> -0.91668062 | F16: Actual
A18: Check: bridge end vs. Variance tab actual (must be 0) | B18: =ROUND(B16-Variance!$D$19,6) -> 0 | C18: =ROUND(C16-Variance!$D$24,6) -> 0
A19: Reported adj. EPS vs. guided EPS (headline variance) | C19: =Inputs!$C$34-Inputs!$C$18 -> 0.08
